setup.py
ascii_ruler/__init__.py
ascii_ruler/__main__.py
ascii_ruler.egg-info/PKG-INFO
ascii_ruler.egg-info/SOURCES.txt
ascii_ruler.egg-info/dependency_links.txt
ascii_ruler.egg-info/entry_points.txt
ascii_ruler.egg-info/top_level.txt